snowcone/__init__.py
snowcone/containers.py
tests/__init__.py
tests/test_containers.py
snowcone-0.3.0.dist-info/METADATA
snowcone-0.3.0.dist-info/WHEEL
snowcone-0.3.0.dist-info/top_level.txt
snowcone-0.3.0.dist-info/RECORD
