Metadata-Version: 2.1
Name: snowcone
Version: 0.3.0
Summary: Useful utilities for Python
Home-page: https://www.github.com/ismailuddin/snowcone
Author: Ismail Uddin
License: MIT license
Keywords: array,snowcone,loaded
Platform: UNKNOWN
Classifier: Development Status :: 2 - Pre-Alpha
Classifier: Intended Audience :: Developers
Classifier: License :: OSI Approved :: MIT License
Classifier: Natural Language :: English
Classifier: Programming Language :: Python :: 3
Classifier: Programming Language :: Python :: 3.6
Classifier: Programming Language :: Python :: 3.7
Classifier: Programming Language :: Python :: 3.8
Classifier: Programming Language :: Python :: 3.9
Classifier: Programming Language :: Python :: 3.10
